harmony/__init__.py
harmony/core.py
harmony/plot.py
harmony/utils.py
harmony/version.py
harmonyTS-0.1.5.dist-info/LICENSE
harmonyTS-0.1.5.dist-info/METADATA
harmonyTS-0.1.5.dist-info/WHEEL
harmonyTS-0.1.5.dist-info/top_level.txt
harmonyTS-0.1.5.dist-info/RECORD
