Metadata-Version: 2.1
Name: harmonyTS
Version: 0.1.5
Summary: Harmony is a unified framework for data visualization, analysis and interpretation of scRNA-seq data measured across discrete time points
Home-page: https://github.com/dpeerlab/harmony
Author: Manu Setty
Author-email: manu.talanki@gmail.com
Classifier: Programming Language :: Python :: 3
Classifier: License :: OSI Approved :: MIT License
Classifier: Operating System :: OS Independent
Classifier: Operating System :: POSIX :: Linux
Classifier: Development Status :: 5 - Production/Stable
Classifier: Topic :: Scientific/Engineering :: Bio-Informatics
Classifier: Topic :: Scientific/Engineering :: Visualization
Requires-Python: >=3.6
License-File: LICENSE
Requires-Dist: numpy >=1.14.2
Requires-Dist: pandas >=0.22.0
Requires-Dist: scipy >=1.0.1
Requires-Dist: scikit-learn
Requires-Dist: fa2
Requires-Dist: matplotlib >=2.2.2
Requires-Dist: seaborn >=0.8.1
Requires-Dist: palantir >=0.2.3
Requires-Dist: scanpy
